BlockFrame/__init__.py
BlockFrame/block_frame.py
BlockFrame/chunking_service/__init__.py
BlockFrame/chunking_service/chunking.py
BlockFrame/chunking_service/config.py
BlockFrame/chunking_service/fetcher.py
BlockFrame/database_service/__init__.py
BlockFrame/database_service/database.py
BlockFrame/database_service/defaultmodel.py
BlockFrame/database_service/getters.py
BlockFrame/database_service/initalisation.py
BlockFrame/database_service/setters.py
BlockFrame-1.1.0.dist-info/METADATA
BlockFrame-1.1.0.dist-info/WHEEL
BlockFrame-1.1.0.dist-info/top_level.txt
BlockFrame-1.1.0.dist-info/RECORD
