Metadata-Version: 2.1
Name: BlockFrame
Version: 1.1.0
Summary: File Chunking Library to work as a data-store solution alongside webapps and software.
Home-page: https://github.com/Wizock/BlockFrame/
Author: Rohaan Ahmed
Author-email: silent.death3500@gmail.com
Project-URL: Bug Tracker, https://github.com/Wizock/BlockFrame/issues
Project-URL: Documentation, https://blockframe.readthedocs.io/
Project-URL: Source Code, https://github.com/Wizock/BlockFrame/
Keywords: file chunking,chunker,sqlalchemy,config,data-store,webapps,software
Classifier: Development Status :: 3 - Alpha
Classifier: License :: OSI Approved :: MIT License
Classifier: Programming Language :: Python :: 3
Classifier: Programming Language :: Python :: 3.6
Classifier: Programming Language :: Python :: 3.7
Classifier: Programming Language :: Python :: 3.8
Classifier: Programming Language :: Python :: 3.9
Classifier: Programming Language :: Python :: 3.10
Classifier: Programming Language :: Python :: 3.11
Requires-Python: >=3.6
Requires-Dist: cryptography
Requires-Dist: SQLAlchemy
Requires-Dist: setuptools
Requires-Dist: wheel
Requires-Dist: aiosqlite
